testPyPiPP/__init__.py
testPyPiPP/m_mod_pp.py
testPyPiPP-0.0.1.dist-info/METADATA
testPyPiPP-0.0.1.dist-info/WHEEL
testPyPiPP-0.0.1.dist-info/license.txt
testPyPiPP-0.0.1.dist-info/top_level.txt
testPyPiPP-0.0.1.dist-info/RECORD
