Metadata-Version: 2.1
Name: testPyPiPP
Version: 0.0.1
Summary: My test package
Author-email: AZ <pawel.przybyla@gmail.com>
License: MIT License
Keywords: testPyPiPP,name,surname,fun function
Classifier: Framework :: Odoo
Classifier: Framework :: Pytest
Requires-Python: >=3.0
License-File: license.txt
Requires-Dist: numpy
